astro_void_finder-0.2.0.dist-info/licenses/LICENSE
astrolib/__init__.py
astrolib/acceleration_structures.py
astrolib/cache.py
astrolib/cosmology.py
astrolib/nbody.py
astrolib/neutrino.py
astrolib/neutrino_ml.py
astrolib/optimized_nbody.py
astrolib/optimized_voids.py
astrolib/resource_manager.py
astrolib/visualization.py
astrolib/void_analysis.py
astrolib/voidfinder.py
astro_void_finder-0.2.0.dist-info/METADATA
astro_void_finder-0.2.0.dist-info/WHEEL
astro_void_finder-0.2.0.dist-info/top_level.txt
astro_void_finder-0.2.0.dist-info/RECORD
