Metadata-Version: 2.4
Name: astro-void-finder
Version: 0.2.0
Summary: High-performance astrophysics library for void finding, neutrino physics, and N-body simulations
Home-page: https://github.com/JFBookwood/astro-void-finder
Author: JFBookwood
Author-email: jesse.buchholz@jgmm.de
Keywords: astronomy astrophysics cosmology voids neutrinos n-body simulation
Classifier: Development Status :: 4 - Beta
Classifier: Intended Audience :: Science/Research
Classifier: License :: OSI Approved :: MIT License
Classifier: Programming Language :: Python :: 3.8
Classifier: Programming Language :: Python :: 3.9
Classifier: Programming Language :: Python :: 3.10
Classifier: Programming Language :: Python :: 3.11
Classifier: Programming Language :: Python :: 3.12
Classifier: Topic :: Scientific/Engineering :: Astronomy
Classifier: Topic :: Scientific/Engineering :: Physics
Requires-Python: >=3.8
License-File: LICENSE
Requires-Dist: numpy>=1.20.0
Requires-Dist: scipy>=1.7.0
Requires-Dist: astropy>=4.0
Requires-Dist: numba>=0.55.0
Requires-Dist: h5py>=3.0.0
Requires-Dist: matplotlib>=3.4.0
Requires-Dist: pandas>=1.3.0
Requires-Dist: scikit-learn>=1.0.0
Requires-Dist: psutil>=5.8.0
Dynamic: author
Dynamic: author-email
Dynamic: classifier
Dynamic: description
Dynamic: description-content-type
Dynamic: home-page
Dynamic: keywords
Dynamic: license-file
Dynamic: requires-dist
Dynamic: requires-python
Dynamic: summary
